setup.py
image_match/__init__.py
image_match/elasticsearch_driver.py
image_match/goldberg.py
image_match/mongodb_driver.py
image_match/signature_database_base.py
image_match.egg-info/PKG-INFO
image_match.egg-info/SOURCES.txt
image_match.egg-info/dependency_links.txt
image_match.egg-info/requires.txt
image_match.egg-info/top_level.txt
image_match.egg-info/zip-safe
tests/__init__.py
tests/test_elasticsearch_driver.py
tests/test_goldberg.py