Metadata-Version: 1.1
Name: image-match
Version: 1.1.0
Summary: image_match is a simple package for finding approximate image matches from a corpus.
Home-page: https://github.com/ascribe/image-match/
Author: Ryan Henderson
Author-email: ryan@bigchaindb.com
License: Apache License 2.0
Platform: UNKNOWN
Classifier: Development Status :: 4 - Beta
Classifier: Intended Audience :: Developers
Classifier: Topic :: Database
Classifier: Topic :: Database :: Database Engines/Servers
Classifier: Topic :: Software Development
Classifier: Natural Language :: English
Classifier: License :: OSI Approved :: Apache Software License
Classifier: Programming Language :: Python :: 3
Classifier: Programming Language :: Python :: 3.4
Classifier: Operating System :: MacOS :: MacOS X
Classifier: Operating System :: POSIX :: Linux
Classifier: Topic :: Multimedia :: Graphics
